news_corpus_builder
