Metadata-Version: 1.1
Name: news-corpus-builder
Version: 0.1.4
Summary: Quickly build a news/web corpus with specifc topics or terms automatically from Google News or by specifying                 article links in a file. This module automatically extracts the body and title from each article and saves                the result to either flatfiles or sqlite database.
Home-page: https://github.com/skillachie/news_corpus_builder
Author: Dwayne V Campbell
Author-email: dwaynecampbell13 _at_ gmail.com
License: MIT License
Download-URL: https://github.com/skillachie/news_corpus_builder
Keywords: corpus, nlp news,extractor,web scrapping, natural language processing
Platform: UNKNOWN
Classifier: Development Status :: 4 - Beta
Classifier: Intended Audience :: Developers
Classifier: License :: OSI Approved :: MIT LicenseTopic :: Software Development :: Libraries :: Python Modules
Classifier: Topic :: Text Processing
Classifier: Topic :: Text Processing :: General
Classifier: Topic :: Utilities
Classifier: Topic :: Scientific/Engineering
